plexmatch.py
plexmatch-0.1.1.dist-info/LICENSE
plexmatch-0.1.1.dist-info/WHEEL
plexmatch-0.1.1.dist-info/METADATA
plexmatch-0.1.1.dist-info/RECORD
